{
  "end": "676bf381",
  "start": "34614",
  "format": "34614:{}:{:x}:676bf381",
  "prefix": "34614",
  "suffix": "676bf381",
  "revision": "202412251158-59f3a32c88",
  "app_token": "33d57ade8c02dbc5a333db99ff9ae26a",
  "static_param": "5Nm83JFVAztbEFoHXQh4MFNoScWPleSN",
  "remove_headers": [
    "user_id"
  ],
  "checksum_indexes": [
    1,
    1,
    2,
    3,
    3,
    4,
    7,
    10,
    10,
    12,
    12,
    13,
    14,
    14,
    14,
    15,
    17,
    24,
    24,
    25,
    26,
    26,
    27,
    29,
    31,
    32,
    33,
    34,
    36,
    36,
    37,
    38
  ],
  "checksum_constant": 368
}