{
  "end": "670e98bc",
  "start": "31124",
  "format": "31124:{}:{:x}:670e98bc",
  "prefix": "31124",
  "suffix": "670e98bc",
  "revision": "202410151630-9731885bab",
  "app_token": "33d57ade8c02dbc5a333db99ff9ae26a",
  "static_param": "Ah0Ek24DmZxFGCu7rxSkFCJufVfz7QJk",
  "remove_headers": [
    "user_id"
  ],
  "checksum_indexes": [
    1,
    2,
    3,
    4,
    4,
    5,
    8,
    10,
    10,
    11,
    11,
    12,
    13,
    17,
    18,
    20,
    21,
    21,
    24,
    24,
    25,
    25,
    25,
    25,
    26,
    27,
    31,
    31,
    31,
    34,
    35,
    35
  ],
  "checksum_constant": 194
}